xtheme/__init__.py
xtheme/generators.py
xtheme/helpers.py
xtheme/themes.py
xtheme-0.3.dist-info/METADATA
xtheme-0.3.dist-info/RECORD
xtheme-0.3.dist-info/WHEEL
xtheme-0.3.dist-info/entry_points.txt
xtheme-0.3.dist-info/top_level.txt
