Metadata-Version: 2.1
Name: xtheme
Version: 0.3
Summary: theme generator
Home-page: http://github.com/rtgnx/xtheme
Author: Adrian Cybulski
Author-email: adrian@rtgnx.xyz
License: GPL2
Platform: UNKNOWN
Classifier: Programming Language :: Python :: 3
Classifier: License :: OSI Approved :: GNU General Public License v2 (GPLv2)
Classifier: Operating System :: POSIX :: Linux
Requires-Dist: click
Requires-Dist: toml
Requires-Dist: jinja2
